<?xml version="1.0" encoding="UTF-8"?>
<xliff version="1.0">
  <file source-language="EN" target-language="pt" datatype="plaintext" original="messages" date="2011-11-07T09:25:02Z" product-name="messages">
    <body>
      <trans-unit id="8">
        <source>Title</source>
        <target>Título</target>
      </trans-unit>
      <trans-unit id="40">
        <source>Identity area</source>
        <target>Área de identificação</target>
      </trans-unit>
      <trans-unit id="41">
        <source>Reference code</source>
        <target>Código de referência</target>
      </trans-unit>
      <trans-unit id="43">
        <source>Note</source>
        <target>nota</target>
      </trans-unit>
      <trans-unit id="48">
        <source>Level of description</source>
        <target>Nível de descrição</target>
      </trans-unit>
      <trans-unit id="51">
        <source>Context area</source>
        <target>Área de contextualização</target>
      </trans-unit>
      <trans-unit id="62">
        <source>Repository</source>
        <target>Entidade custodiadora</target>
      </trans-unit>
      <trans-unit id="70">
        <source>Conditions governing access</source>
        <target>Condições de acesso</target>
      </trans-unit>
      <trans-unit id="80">
        <source>Subject access points</source>
        <target>pontos de acesso - assunto</target>
      </trans-unit>
      <trans-unit id="81">
        <source>Place access points</source>
        <target>Pontos de acesso - lugares</target>
      </trans-unit>
      <trans-unit id="85">
        <source>Institution identifier</source>
        <target>identificador da instituição</target>
      </trans-unit>
      <trans-unit id="86">
        <source>Status</source>
        <target>Status</target>
      </trans-unit>
      <trans-unit id="87">
        <source>Level of detail</source>
        <target>nível de detalhamento</target>
      </trans-unit>
      <trans-unit id="88">
        <source>Dates of creation, revision and deletion</source>
        <target>datas das descrições (criação, revisão e remoção)</target>
      </trans-unit>
      <trans-unit id="91">
        <source>Sources</source>
        <target>fontes</target>
      </trans-unit>
      <trans-unit id="120">
        <source>Identifier</source>
        <target>Código de referência</target>
      </trans-unit>
      <trans-unit id="207">
        <source>Type</source>
        <target>tipo</target>
      </trans-unit>
      <trans-unit id="247">
        <source>Control area</source>
        <target>área de controle</target>
      </trans-unit>
      <trans-unit id="300">
        <source>Description identifier</source>
        <target>identificador da descrição</target>
      </trans-unit>
      <trans-unit id="333">
        <source>Date</source>
        <target>data</target>
      </trans-unit>
      <trans-unit id="471">
        <source>Date(s)</source>
        <target>Data(s)</target>
      </trans-unit>
      <trans-unit id="765">
        <source>Edit identity area</source>
        <target/>
      </trans-unit>
      <trans-unit id="766">
        <source>Edit context area</source>
        <target/>
      </trans-unit>
      <trans-unit id="800">
        <source>Rules or conventions</source>
        <target/>
      </trans-unit>
      <trans-unit id="815">
        <source>Appraisal, destruction and scheduling</source>
        <target/>
      </trans-unit>
      <trans-unit id="818">
        <source>System of arrangement</source>
        <target/>
      </trans-unit>
      <trans-unit id="822">
        <source>Conditions governing reproduction</source>
        <target/>
      </trans-unit>
      <trans-unit id="824">
        <source>Physical characteristics and technical requirements</source>
        <target/>
      </trans-unit>
      <trans-unit id="827">
        <source>Existence and location of originals</source>
        <target/>
      </trans-unit>
      <trans-unit id="829">
        <source>Existence and location of copies</source>
        <target/>
      </trans-unit>
      <trans-unit id="831">
        <source>Related units of description</source>
        <target/>
      </trans-unit>
    </body>
  </file>
</xliff>
